Metadata-Version: 1.1
Name: electron-inject-dark-slack
Version: 0.3.4
Summary: A fork of electron-inject to inject a dark css theme into the slack desktop app
Home-page: https://github.com/KemonoServal/electron-inject-dark-slack
Author: KemonoServal
Author-email: wrdqex@gmail.com
License: GPLv3
Download-URL: https://github.com/KemonoServal/electron-inject-dark-slack/tarball/v0.3
Keywords: electron,inject,slack,dark theme
Platform: UNKNOWN
